en2cn/__init__.py
en2cn/中文词典.py
en2cn/翻译/__init__.py
en2cn/翻译/数据类型.py
en2cn/翻译/自定义词典.py
en2cn/翻译/词典相关常量.py
en2cn/词典数据/词典0.ts
en2cn/词典数据/词典1.ts
en2cn/词典数据/词典10.ts
en2cn/词典数据/词典11.ts
en2cn/词典数据/词典12.ts
en2cn/词典数据/词典13.ts
en2cn/词典数据/词典14.ts
en2cn/词典数据/词典15.ts
en2cn/词典数据/词典2.ts
en2cn/词典数据/词典3.ts
en2cn/词典数据/词典4.ts
en2cn/词典数据/词典5.ts
en2cn/词典数据/词典6.ts
en2cn/词典数据/词典7.ts
en2cn/词典数据/词典8.ts
en2cn/词典数据/词典9.ts
en2cn/词典数据/词形变化.ts
en2cn-0.40.dist-info/METADATA
en2cn-0.40.dist-info/RECORD
en2cn-0.40.dist-info/WHEEL
en2cn-0.40.dist-info/top_level.txt
