Metadata-Version: 2.1
Name: en2cn
Version: 0.40
Summary: 英文翻译到中文的包
Home-page: https://github.com/pebble329/en2cn-
Author: pebble329
Author-email: pebble329@126.com
License: UNKNOWN
Platform: UNKNOWN
Classifier: Programming Language :: Python :: 3
Classifier: License :: OSI Approved :: MIT License
Classifier: Operating System :: OS Independent
Requires-Python: >=3.6
